.deepsource.toml
LICENSE
MANIFEST.in
README.md
requirements.txt
setup.cfg
setup.py
rq/__init__.py
rq/command.py
rq/connections.py
rq/decorators.py
rq/defaults.py
rq/dummy.py
rq/exceptions.py
rq/job.py
rq/local.py
rq/logutils.py
rq/queue.py
rq/registry.py
rq/scheduler.py
rq/serializers.py
rq/suspension.py
rq/timeouts.py
rq/utils.py
rq/version.py
rq/worker.py
rq/worker_registration.py
rq/cli/__init__.py
rq/cli/__main__.py
rq/cli/cli.py
rq/cli/helpers.py
rq/compat/__init__.py
rq/compat/connections.py
rq/compat/dictconfig.py
rq/contrib/__init__.py
rq/contrib/legacy.py
rq/contrib/sentry.py
rq27.egg-info/PKG-INFO
rq27.egg-info/SOURCES.txt
rq27.egg-info/dependency_links.txt
rq27.egg-info/entry_points.txt
rq27.egg-info/not-zip-safe
rq27.egg-info/requires.txt
rq27.egg-info/top_level.txt